treon/__init__.py
treon/__main__.py
treon/task.py
treon/test_execution.py
treon/treon.py
treon-0.1.4.dist-info/LICENSE
treon-0.1.4.dist-info/METADATA
treon-0.1.4.dist-info/WHEEL
treon-0.1.4.dist-info/entry_points.txt
treon-0.1.4.dist-info/top_level.txt
treon-0.1.4.dist-info/RECORD
