Metadata-Version: 2.1
Name: treon
Version: 0.1.4
Summary: Testing framework for Jupyter Notebooks
Home-page: https://github.com/reviewNB/treon
Author: Amit Rathi
Author-email: amit@reviewnb.com
License: MIT
Keywords: test,jupyter,notebook,jupyter test,notebook test,unittest,doctest
Platform: UNKNOWN
Requires-Python: >=3
Requires-Dist: nbconvert
Requires-Dist: jupyter-client
Requires-Dist: jupyter
Requires-Dist: docopt
